blendSubRender/Render.py
blendSubRender/__init__.py
blendSubRender/blendSubRender.py
blendSubRender-0.1.0.dist-info/LICENSE
blendSubRender-0.1.0.dist-info/METADATA
blendSubRender-0.1.0.dist-info/WHEEL
blendSubRender-0.1.0.dist-info/top_level.txt
blendSubRender-0.1.0.dist-info/RECORD
